rusty_rlp-0.4.0.dist-info/METADATA
rusty_rlp-0.4.0.dist-info/WHEEL
rusty_rlp-0.4.0.dist-info/license_files/LICENSE
rusty_rlp/__init__.py
rusty_rlp/rusty_rlp.cp39-win_amd64.pyd
rusty_rlp-0.4.0.dist-info/RECORD
