Metadata-Version: 2.3
Name: rusty-rlp
Version: 0.4.0
Classifier: Intended Audience :: Developers
Classifier: Programming Language :: Rust
Classifier: License :: OSI Approved :: MIT License
Classifier: Natural Language :: English
Classifier: Programming Language :: Python :: 3
Classifier: Programming Language :: Python :: 3.8
Classifier: Programming Language :: Python :: 3.9
Classifier: Programming Language :: Python :: 3.10
Classifier: Programming Language :: Python :: 3.11
Classifier: Programming Language :: Python :: 3.12
License-File: LICENSE
Summary: Python RLP serialization/deserialization based on a rapid fast Rust implementation.
Home-Page: https://github.com/cburgdorf/rusty-rlp
Author: Christoph Burgdorf <christoph.burgdorf@gmail.com>
Author-email: Christoph Burgdorf <christoph.burgdorf@gmail.com>
License: MIT
Project-URL: Source Code, https://github.com/cburgdorf/rusty-rlp
